warlocksfx/__init__.py
warlocksfx/warlocksfx.py
warlockSFX-0.2.1.dist-info/LICENSE
warlockSFX-0.2.1.dist-info/METADATA
warlockSFX-0.2.1.dist-info/WHEEL
warlockSFX-0.2.1.dist-info/entry_points.txt
warlockSFX-0.2.1.dist-info/top_level.txt
warlockSFX-0.2.1.dist-info/RECORD
