Metadata-Version: 2.1
Name: warlockSFX
Version: 0.2.1
Summary: warlockSFX is a part of warlock (Data Breach protection software), and is based on pymakeself by Andrew Gillis.
Author-email: Soumyo Deep Gupta <deep.main.ac@gmail.com>
Maintainer-email: Soumyo Deep Gupta <deep.main.ac@gmail.com>
License: MIT License
Project-URL: Homepage, http://github.com/d33pster/warlockSFX
Project-URL: Issues, http://github.com/d33pster/warlockSFX/issues
Keywords: d33pster,pymakeself,pymakeself alternative,makesfx,warlock,warlocksfx
Classifier: Development Status :: 4 - Beta
Classifier: Intended Audience :: Developers
Classifier: Programming Language :: Python :: 3.9
Classifier: Programming Language :: Python :: 3.10
Classifier: Programming Language :: Python :: 3.11
Classifier: Programming Language :: Python :: 3.12
Classifier: License :: OSI Approved :: MIT License
Classifier: Operating System :: OS Independent
Requires-Python: >=3.9
License-File: LICENSE
Requires-Dist: argparse
Requires-Dist: pyinstaller
Requires-Dist: optioner >=1.4.1
Requires-Dist: colorama
